datahints/__init__.py
datahints/datahints.py
datahints-0.1.1.dist-info/LICENSE.txt
datahints-0.1.1.dist-info/WHEEL
datahints-0.1.1.dist-info/METADATA
datahints-0.1.1.dist-info/RECORD
