Metadata-Version: 2.1
Name: datahints
Version: 0.1.1
Summary: Type hinting for pandas DataFrame
Home-page: https://github.com/litek/datahints
License: MIT
Author: Ketil Albertsen
Requires-Python: >=3.9,<4.0
Classifier: License :: OSI Approved :: MIT License
Classifier: Programming Language :: Python :: 3
Classifier: Programming Language :: Python :: 3.9
Project-URL: Repository, https://github.com/litek/datahints
